dbt_af/__init__.py
dbt_af/dags.py
dbt_af/builder/__init__.py
dbt_af/builder/backfill_dag_components.py
dbt_af/builder/dag_components.py
dbt_af/builder/dbt_af_builder.py
dbt_af/builder/dbt_model_path_graph_builder.py
dbt_af/builder/domain_dag.py
dbt_af/builder/maintenance_dag_components.py
dbt_af/builder/task_dependencies.py
dbt_af/common/__init__.py
dbt_af/common/af_callbacks.py
dbt_af/common/af_scheduling_utils.py
dbt_af/common/constants.py
dbt_af/common/cron.py
dbt_af/common/scheduling.py
dbt_af/common/utils.py
dbt_af/conf/__init__.py
dbt_af/conf/config.py
dbt_af/integrations/__init__.py
dbt_af/integrations/af_callbacks/__init__.py
dbt_af/integrations/af_callbacks/callbacks.py
dbt_af/integrations/mcd/__init__.py
dbt_af/integrations/mcd/callbacks.py
dbt_af/integrations/mcd/dbt_core.py
dbt_af/integrations/tableau/__init__.py
dbt_af/integrations/tableau/auth.py
dbt_af/integrations/tableau/exceptions.py
dbt_af/integrations/tableau/extracts.py
dbt_af/operators/__init__.py
dbt_af/operators/base.py
dbt_af/operators/branch.py
dbt_af/operators/kubernetes_pod.py
dbt_af/operators/macros.py
dbt_af/operators/run.py
dbt_af/operators/sensors.py
dbt_af/operators/supplemental.py
dbt_af/operators/venv.py
dbt_af/parser/__init__.py
dbt_af/parser/dbt_node_model.py
dbt_af/parser/dbt_profiles.py
dbt_af/parser/dbt_source_model.py
dbt_af-0.14.6.dist-info/METADATA
dbt_af-0.14.6.dist-info/WHEEL
dbt_af-0.14.6.dist-info/entry_points.txt
dbt_af-0.14.6.dist-info/licenses/AUTHORS
dbt_af-0.14.6.dist-info/licenses/LICENSE
dbt_af-0.14.6.dist-info/RECORD
