Metadata-Version: 2.4
Name: dbt-af
Version: 0.14.6
Summary: Distibuted dbt runs on Apache Airflow
Author-email: Nikita Yurasov <nikitayurasov@toloka.ai>, Igor Safonov <igsaf@toloka.ai>, Evgeny Ermakov <jkermakov@toloka.ai>, Leonid Kozhinov <lkozhinov@toloka.ai>
License-Expression: Apache-2.0
License-File: AUTHORS
License-File: LICENSE
Keywords: airflow,dbt,python
Requires-Python: <3.13,>=3.10
Requires-Dist: apache-airflow-providers-cncf-kubernetes>=7.0.0
Requires-Dist: apache-airflow<3,>=2.6
Requires-Dist: attrs>=23.1
Requires-Dist: cachetools<7,>=5.3
Requires-Dist: croniter>=3.0
Requires-Dist: dbt-core<2,>=1.7
Requires-Dist: packaging>=21.0
Requires-Dist: pydantic<3.0.0,>=1.10
Requires-Dist: pytest-env>=1.0.0
Requires-Dist: pytest>=7.4.0
Requires-Dist: typer>=0.9
Requires-Dist: virtualenv>=20.27.0
Provides-Extra: all
Requires-Dist: airflow-mcd<0.4.0,>=0.3.3; extra == 'all'
Requires-Dist: pycarlo>=0.9; extra == 'all'
Requires-Dist: setuptools; extra == 'all'
Requires-Dist: tableauserverclient<0.26.0,>=0.25.0; extra == 'all'
Provides-Extra: mcd
Requires-Dist: airflow-mcd<0.4.0,>=0.3.3; extra == 'mcd'
Requires-Dist: pycarlo>=0.9; extra == 'mcd'
Requires-Dist: setuptools; extra == 'mcd'
Provides-Extra: tableau
Requires-Dist: tableauserverclient<0.26.0,>=0.25.0; extra == 'tableau'
